umlet_utils/__init__.py
umlet_utils/python_api_to_umlet.py
umlet_utils/survey_python_code_base.py
umlet_utils/yaml_to_umlet_use_case.py
umlet_utils/umlet/__init__.py
umlet_utils/umlet/file/__init__.py
umlet_utils/umlet/file/writer.py
umlet_utils/umlet/file_system/__init__.py
umlet_utils/umlet/file_system/util.py
umlet_utils/umlet/python/__init__.py
umlet_utils/umlet/python/code_base/__init__.py
umlet_utils/umlet/python/code_base/surveyor.py
umlet_utils/umlet/python/file/__init__.py
umlet_utils/umlet/python/file/parser.py
umlet_utils/umlet/python_to_umlet/__init__.py
umlet_utils/umlet/python_to_umlet/converter.py
umlet_utils/umlet/use_case/__init__.py
umlet_utils/umlet/use_case/file/__init__.py
umlet_utils/umlet/use_case/file/writer.py
umlet_utils/umlet/yaml_to_umlet/__init__.py
umlet_utils/umlet/yaml_to_umlet/use_case/__init__.py
umlet_utils/umlet/yaml_to_umlet/use_case/converter.py
umlet_utils-0.1.0.dist-info/AUTHORS.rst
umlet_utils-0.1.0.dist-info/LICENSE
umlet_utils-0.1.0.dist-info/METADATA
umlet_utils-0.1.0.dist-info/WHEEL
umlet_utils-0.1.0.dist-info/entry_points.txt
umlet_utils-0.1.0.dist-info/top_level.txt
umlet_utils-0.1.0.dist-info/RECORD
